[{
	"city": "江苏省",
	"he": 755,
	"hu": 55,
	"ku": 1378
}, {
	"city": "南京市",
	"he": 48,
	"hu": 3,
	"ku": 251
}, {
	"city": "无锡市",
	"he": 161,
	"hu": 10,
	"ku": 80
}, {
	"city": "徐州市",
	"he": 36,
	"hu": 6,
	"ku": 84
}, {
	"city": "常州市",
	"he": 44,
	"hu": 2,
	"ku": 60
}, {
	"city": "苏州市",
	"he": 51,
	"hu": 3,
	"ku": 20
}, {
	"city": "南通市",
	"he": 120,
	"hu": 5,
	"ku": 180
}, {
	"city": "连云港市",
	"he": 53,
	"hu": 4,
	"ku": 168
}, {
	"city": "淮安市",
	"he": 61,
	"hu": 3,
	"ku": 98
}, {
	"city": "盐城市",
	"he": 12,
	"hu": 3,
	"ku": 100
}, {
	"city": "扬州市",
	"he": 26,
	"hu": 5,
	"ku": 90
}, {
	"city": "镇江市",
	"he": 50,
	"hu": 3,
	"ku": 97
}, {
	"city": "泰州市",
	"he": 31,
	"hu": 3,
	"ku": 60
}, {
	"city": "宿迁市",
	"he": 62,
	"hu": 5,
	"ku": 90
}]